[
{"id":"b1-si-031","level":"B1","topics":["self-improvement"],"front":"die Selbsterkenntnis","back":"self-awareness","exampleSentence":"Selbsterkenntnis ist der erste Schritt zur Veränderung.","exampleTranslation":"Self-awareness is the first step to change.","partOfSpeech":"noun","gender":"die"},
{"id":"b1-si-032","level":"B1","topics":["self-improvement"],"front":"die Selbstreflexion","back":"self-reflection","exampleSentence":"Selbstreflexion hilft mir, bessere Entscheidungen zu treffen.","exampleTranslation":"Self-reflection helps me make better decisions.","partOfSpeech":"noun","gender":"die"},
{"id":"b1-si-033","level":"B1","topics":["self-improvement"],"front":"der innere Frieden","back":"inner peace","exampleSentence":"Beim Yoga finde ich inneren Frieden.","exampleTranslation":"In yoga I find inner peace.","partOfSpeech":"noun phrase","gender":"der"},
{"id":"b1-si-034","level":"B1","topics":["self-improvement"],"front":"die Resilienz","back":"resilience","exampleSentence":"Resilienz kann man trainieren wie einen Muskel.","exampleTranslation":"You can train resilience like a muscle.","partOfSpeech":"noun","gender":"die"},
{"id":"b1-si-035","level":"B1","topics":["self-improvement"],"front":"die Disziplin","back":"discipline","exampleSentence":"Ohne Disziplin kommt man nicht weit.","exampleTranslation":"Without discipline you don't get far.","partOfSpeech":"noun","gender":"die"},
{"id":"b1-si-036","level":"B1","topics":["self-improvement"],"front":"die Vision","back":"vision","exampleSentence":"Jeder braucht eine Vision für sein Leben.","exampleTranslation":"Everyone needs a vision for their life.","partOfSpeech":"noun","gender":"die"},
{"id":"b1-si-037","level":"B1","topics":["self-improvement"],"front":"der Traum","back":"dream","exampleSentence":"Folge deinen Träumen, egal wie verrückt sie sind.","exampleTranslation":"Follow your dreams, no matter how crazy they are.","partOfSpeech":"noun","gender":"der"},
{"id":"b1-si-038","level":"B1","topics":["self-improvement"],"front":"die Berufung","back":"calling, vocation","exampleSentence":"Schreiben ist nicht nur mein Beruf, sondern meine Berufung.","exampleTranslation":"Writing isn't just my job, it's my calling.","partOfSpeech":"noun","gender":"die"},
{"id":"b1-si-039","level":"B1","topics":["self-improvement"],"front":"das Glück","back":"happiness, luck","exampleSentence":"Glück findet man oft in kleinen Dingen.","exampleTranslation":"Happiness is often found in small things.","partOfSpeech":"noun","gender":"das"},
{"id":"b1-si-040","level":"B1","topics":["self-improvement"],"front":"das Wohlbefinden","back":"well-being","exampleSentence":"Mein Wohlbefinden ist mir wichtiger als Geld.","exampleTranslation":"My well-being is more important to me than money.","partOfSpeech":"noun","gender":"das"},
{"id":"b1-si-041","level":"B1","topics":["self-improvement"],"front":"die Routine","back":"routine","exampleSentence":"Eine gute Morgenroutine verändert den Tag.","exampleTranslation":"A good morning routine changes the day.","partOfSpeech":"noun","gender":"die"},
{"id":"b1-si-042","level":"B1","topics":["self-improvement"],"front":"die Selbstpflege","back":"self-care","exampleSentence":"Selbstpflege ist kein Luxus, sondern notwendig.","exampleTranslation":"Self-care isn't a luxury, it's necessary.","partOfSpeech":"noun","gender":"die"},
{"id":"b1-si-043","level":"B1","topics":["self-improvement"],"front":"das Tagebuch","back":"journal, diary","exampleSentence":"Jeden Abend schreibe ich in mein Tagebuch.","exampleTranslation":"Every evening I write in my journal.","partOfSpeech":"noun","gender":"das"},
{"id":"b1-si-044","level":"B1","topics":["self-improvement"],"front":"die Wertschätzung","back":"appreciation","exampleSentence":"Wertschätzung zeigt sich in kleinen Gesten.","exampleTranslation":"Appreciation shows itself in small gestures.","partOfSpeech":"noun","gender":"die"},
{"id":"b1-si-045","level":"B1","topics":["self-improvement"],"front":"das Mitgefühl","back":"compassion","exampleSentence":"Mitgefühl beginnt bei einem selbst.","exampleTranslation":"Compassion begins with yourself.","partOfSpeech":"noun","gender":"das"},
{"id":"b1-si-046","level":"B1","topics":["self-improvement"],"front":"die Akzeptanz","back":"acceptance","exampleSentence":"Akzeptanz bedeutet nicht, alles gut zu finden.","exampleTranslation":"Acceptance doesn't mean liking everything.","partOfSpeech":"noun","gender":"die"},
{"id":"b1-si-047","level":"B1","topics":["self-improvement"],"front":"das Hindernis","back":"obstacle","exampleSentence":"Hindernisse machen uns stärker.","exampleTranslation":"Obstacles make us stronger.","partOfSpeech":"noun","gender":"das"},
{"id":"b1-si-048","level":"B1","topics":["self-improvement"],"front":"der Rückschlag","back":"setback","exampleSentence":"Nach einem Rückschlag wieder aufzustehen ist die Kunst.","exampleTranslation":"Getting up again after a setback is the art.","partOfSpeech":"noun","gender":"der"},
{"id":"b1-si-049","level":"B1","topics":["self-improvement"],"front":"der Erfolg","back":"success","exampleSentence":"Erfolg ist die Summe vieler kleiner Schritte.","exampleTranslation":"Success is the sum of many small steps.","partOfSpeech":"noun","gender":"der"},
{"id":"b1-si-050","level":"B1","topics":["self-improvement"],"front":"das Loslassen","back":"letting go","exampleSentence":"Manchmal ist Loslassen der schwerste Schritt.","exampleTranslation":"Sometimes letting go is the hardest step.","partOfSpeech":"noun","gender":"das"},
{"id":"b1-si-051","level":"B1","topics":["self-improvement"],"front":"meditieren","back":"to meditate","exampleSentence":"Ich meditiere jeden Morgen für zehn Minuten.","exampleTranslation":"I meditate every morning for ten minutes.","partOfSpeech":"verb"},
{"id":"b1-si-052","level":"B1","topics":["self-improvement"],"front":"visualisieren","back":"to visualize","exampleSentence":"Visualisiere dein Ziel jeden Tag.","exampleTranslation":"Visualize your goal every day.","partOfSpeech":"verb"},
{"id":"b1-si-053","level":"B1","topics":["self-improvement"],"front":"scheitern","back":"to fail","exampleSentence":"Wer nie scheitert, lernt auch nichts.","exampleTranslation":"Whoever never fails also learns nothing.","partOfSpeech":"verb"},
{"id":"b1-si-054","level":"B1","topics":["self-improvement"],"front":"sich fokussieren","back":"to focus","exampleSentence":"Fokussiere dich auf das, was du beeinflussen kannst.","exampleTranslation":"Focus on what you can influence.","partOfSpeech":"verb (reflexive)"},
{"id":"b1-si-055","level":"B1","topics":["self-improvement"],"front":"planen","back":"to plan","exampleSentence":"Wer gut plant, hat weniger Stress.","exampleTranslation":"Whoever plans well has less stress.","partOfSpeech":"verb"},
{"id":"b1-si-056","level":"B1","topics":["self-improvement"],"front":"umsetzen","back":"to implement, to put into practice","exampleSentence":"Eine Idee ist nichts wert, wenn man sie nicht umsetzt.","exampleTranslation":"An idea is worthless if you don't implement it.","partOfSpeech":"verb (separable)"},
{"id":"b1-si-057","level":"B1","topics":["self-improvement"],"front":"erreichen","back":"to achieve, to reach","exampleSentence":"Ich habe alle meine Ziele für dieses Jahr erreicht.","exampleTranslation":"I've achieved all my goals for this year.","partOfSpeech":"verb"},
{"id":"b1-si-058","level":"B1","topics":["self-improvement"],"front":"inspirieren","back":"to inspire","exampleSentence":"Sie inspiriert mich jeden Tag aufs Neue.","exampleTranslation":"She inspires me anew every day.","partOfSpeech":"verb"},
{"id":"b1-si-059","level":"B1","topics":["self-improvement"],"front":"ermutigen","back":"to encourage","exampleSentence":"Meine Familie ermutigt mich, meine Träume zu verfolgen.","exampleTranslation":"My family encourages me to follow my dreams.","partOfSpeech":"verb"},
{"id":"b1-si-060","level":"B1","topics":["self-improvement"],"front":"fokussiert","back":"focused","exampleSentence":"Mit einer Tasse Kaffee bin ich fokussierter.","exampleTranslation":"With a cup of coffee I'm more focused.","partOfSpeech":"adjective"},
{"id":"b1-si-061","level":"B1","topics":["self-improvement"],"front":"produktiv","back":"productive","exampleSentence":"Morgens bin ich am produktivsten.","exampleTranslation":"I'm most productive in the morning.","partOfSpeech":"adjective"},
{"id":"b1-si-062","level":"B1","topics":["self-improvement"],"front":"dankbar","back":"grateful","exampleSentence":"Ich bin sehr dankbar für all die Möglichkeiten.","exampleTranslation":"I'm very grateful for all the opportunities.","partOfSpeech":"adjective"},
{"id":"b1-si-063","level":"B1","topics":["self-improvement"],"front":"erfüllt","back":"fulfilled","exampleSentence":"Nach diesem Projekt fühle ich mich erfüllt.","exampleTranslation":"After this project I feel fulfilled.","partOfSpeech":"adjective"},
{"id":"b1-si-064","level":"B1","topics":["self-improvement"],"front":"die Komfortzone verlassen","back":"to leave the comfort zone","exampleSentence":"Nur wer seine Komfortzone verlässt, wächst.","exampleTranslation":"Only those who leave their comfort zone grow.","partOfSpeech":"verb phrase"},
{"id":"b1-si-065","level":"B1","topics":["self-improvement"],"front":"die Atmung","back":"breathing","exampleSentence":"Bewusste Atmung beruhigt das Nervensystem.","exampleTranslation":"Conscious breathing calms the nervous system.","partOfSpeech":"noun","gender":"die"}
]
